tronpytool/__init__.py
tronpytool/constants.py
tronpytool/contract.py
tronpytool/exceptions.py
tronpytool/main.py
tronpytool/manager.py
tronpytool/module.py
tronpytool/payment.py
tronpytool/transactionbuilder.py
tronpytool/tronbrew.py
tronpytool/trx.py
tronpytool/common/__init__.py
tronpytool/common/abi.py
tronpytool/common/account.py
tronpytool/common/blocks.py
tronpytool/common/contracts.py
tronpytool/common/datastructures.py
tronpytool/common/datatypes.py
tronpytool/common/encoding.py
tronpytool/common/formatters.py
tronpytool/common/key.py
tronpytool/common/normalizers.py
tronpytool/common/threads.py
tronpytool/common/transactions.py
tronpytool/common/validation.py
tronpytool/common/attrdict/__init__.py
tronpytool/common/attrdict/default.py
tronpytool/common/attrdict/dictionary.py
tronpytool/common/attrdict/mapping.py
tronpytool/common/attrdict/merge.py
tronpytool/common/attrdict/mixins.py
tronpytool/common/toolz/__init__.py
tronpytool/common/trc20/__init__.py
tronpytool/compile/__init__.py
tronpytool/compile/basecore.py
tronpytool/compile/basetest.py
tronpytool/compile/bulkmanager.py
tronpytool/compile/commoncompile.py
tronpytool/compile/compile.py
tronpytool/compile/paths.py
tronpytool/compile/service.py
tronpytool/extern/__init__.py
tronpytool/extern/bulkmanager.py
tronpytool/pen/__init__.py
tronpytool/pen/collectfundscn.py
tronpytool/pen/contracttest.py
tronpytool/pen/eventtest.py
tronpytool/pen/membertest.py
tronpytool/providers/__init__.py
tronpytool/providers/base.py
tronpytool/providers/gracefulinterrupter.py
tronpytool/providers/http.py
tronpytool/providers/simulateplayer.py
tronpytool-3.6.82.dist-info/LICENSE
tronpytool-3.6.82.dist-info/METADATA
tronpytool-3.6.82.dist-info/WHEEL
tronpytool-3.6.82.dist-info/top_level.txt
tronpytool-3.6.82.dist-info/RECORD
